.DS_Store
ocrfixr/__init__.py
ocrfixr/run_ocrfixr.py
ocrfixr/spellcheck.py
ocrfixr/unsplit.py
ocrfixr/data/.DS_Store
ocrfixr/data/Ignore_These_Misspells.txt
ocrfixr/data/Ignore_These_Suggestions.txt
ocrfixr/data/SCOWL_20.txt
ocrfixr/data/SCOWL_70.txt
ocrfixr/data/Scannos_Common.txt
ocrfixr/data/Scannos_Stealth.txt
tests/.DS_Store
tests/__init__.py
tests/test_spellcheck.py
tests/test_unsplit.py
OCRfixr-1.5.1.dist-info/LICENSE
OCRfixr-1.5.1.dist-info/METADATA
OCRfixr-1.5.1.dist-info/WHEEL
OCRfixr-1.5.1.dist-info/entry_points.txt
OCRfixr-1.5.1.dist-info/top_level.txt
OCRfixr-1.5.1.dist-info/RECORD
