Metadata-Version: 2.1
Name: OCRfixr
Version: 1.5.1
Summary: A contextual spellchecker for OCR output
Home-page: https://github.com/ja-mcm/ocrfixr
Author: Jack McMahon
Author-email: OCRfixr@mcmahon.work
License: GNU General Public License v3
Keywords: ocrfixr,spellcheck,OCR,contextual,BERT
Platform: UNKNOWN
Classifier: Programming Language :: Python :: 3
Classifier: License :: OSI Approved :: MIT License
Classifier: Operating System :: OS Independent
Requires-Python: >=3.6
License-File: LICENSE
Requires-Dist: transformers
Requires-Dist: tensorflow (>=2.0)
Requires-Dist: numpy (>=1.20.0)
Requires-Dist: symspellpy
Requires-Dist: importlib-resources
Requires-Dist: metaphone
Requires-Dist: tqdm
